allocation.py
bandit.py
darts_berkeley-0.0.2.dist-info/LICENSE
darts_berkeley-0.0.2.dist-info/METADATA
darts_berkeley-0.0.2.dist-info/WHEEL
darts_berkeley-0.0.2.dist-info/top_level.txt
darts_berkeley-0.0.2.dist-info/RECORD
